glioma/__coconut__.py
glioma/__init__.py
glioma/containers.py
glioma/either.py
glioma/option.py
Glioma-1.0.2.dist-info/LICENSE
Glioma-1.0.2.dist-info/METADATA
Glioma-1.0.2.dist-info/WHEEL
Glioma-1.0.2.dist-info/top_level.txt
Glioma-1.0.2.dist-info/RECORD
